CHANGELOG.md
LICENSE
README.md
examples/README.md
examples/extra_examples/README.md
ledshim/__init__.py
ledshim/is31fl3731.py
ledshim-0.0.3.dist-info/METADATA
ledshim-0.0.3.dist-info/WHEEL
ledshim-0.0.3.dist-info/licenses/LICENSE
ledshim-0.0.3.dist-info/RECORD
