Metadata-Version: 2.3
Name: ledshim
Version: 0.0.3
Summary: LED SHIM Driver
Project-URL: GitHub, https://www.github.com/pimoroni/led-shim
Project-URL: Homepage, https://www.pimoroni.com
Author-email: Philip Howard <phil@pimoroni.com>
Maintainer-email: Philip Howard <phil@pimoroni.com>
License: MIT License
Keywords: Pi,Raspberry
Classifier: Development Status :: 4 - Beta
Classifier: Intended Audience :: Developers
Classifier: License :: OSI Approved :: MIT License
Classifier: Operating System :: POSIX :: Linux
Classifier: Programming Language :: Python :: 3
Classifier: Programming Language :: Python :: 3 :: Only
Classifier: Programming Language :: Python :: 3.7
Classifier: Programming Language :: Python :: 3.8
Classifier: Programming Language :: Python :: 3.9
Classifier: Programming Language :: Python :: 3.10
Classifier: Programming Language :: Python :: 3.11
Classifier: Topic :: Software Development
Classifier: Topic :: Software Development :: Libraries
Classifier: Topic :: System :: Hardware
Requires-Python: >=3.7
Requires-Dist: smbus2
